.gitignore
MANIFEST.in
README.md
RELEASES.md
setup.cfg
setup.py
Examples/Example1/README.rst
Examples/Example1/atmo_models.txt
Examples/Example1/data.txt
Examples/Example1/example1.pdf
Examples/Example1/example1.py
Examples/Example1/generate_data_example1.py
Examples/Example1/mock_g.txt
Examples/Example1/mock_i.txt
Examples/Example1/photometric_bands
Examples/Example2/README.rst
Examples/Example2/example2_sun.py
Examples/Example2/example2_vega.py
Examples/Example2/photometric_bands
Examples/Example3/README.rst
Examples/Example3/example3.py
Icarus/__init__.py
Icarus.egg-info/PKG-INFO
Icarus.egg-info/SOURCES.txt
Icarus.egg-info/dependency_links.txt
Icarus.egg-info/requires.txt
Icarus.egg-info/top_level.txt
Icarus/Atmosphere/Atmo.py
Icarus/Atmosphere/Atmo_grid_lithium.py
Icarus/Atmosphere/Atmo_grid_lithium_doppler.py
Icarus/Atmosphere/Atmo_photo_AGSS_COND_LIMBDARK.py
Icarus/Atmosphere/Atmo_photo_BTSettl7.py
Icarus/Atmosphere/Atmo_spectro.py
Icarus/Atmosphere/Atmo_spectro_AGSS_COND_A1FITS.py
Icarus/Atmosphere/Atmo_spectro_BTSettl7.py
Icarus/Atmosphere/Atmo_spectro_IRTF.py
Icarus/Atmosphere/__init__.py
Icarus/Core/Star.py
Icarus/Core/Star_base.py
Icarus/Core/Star_disk.py
Icarus/Core/Star_temperature.py
Icarus/Core/__init__.py
Icarus/CoreBinary/StarBinary.py
Icarus/CoreBinary/__init__.py
Icarus/Photometry/Photometry.py
Icarus/Photometry/Photometry_disk.py
Icarus/Photometry/Photometry_doppler.py
Icarus/Photometry/Photometry_legacy.py
Icarus/Photometry/Photometry_temperature.py
Icarus/Photometry/__init__.py
Icarus/Spectroscopy/Spectroscopy.py
Icarus/Spectroscopy/__init__.py
Icarus/Utils/Binary.py
Icarus/Utils/Eclipse.py
Icarus/Utils/Filter.py
Icarus/Utils/Flux.py
Icarus/Utils/Grid.py
Icarus/Utils/Logger.py
Icarus/Utils/Misc.py
Icarus/Utils/Series.py
Icarus/Utils/Spherical_harmonics.py
Icarus/Utils/Tessellation.py
Icarus/Utils/__init__.py
Icarus/Utils/import_modules.py
Icarus/geodesic/geodesic_n3.txt
Icarus/geodesic/geodesic_n4.txt
Icarus/geodesic/geodesic_n5.txt
Icarus/geodesic/geodesic_n6.txt
Icarus/geodesic/geodesic_n7.txt
Icarus/geodesic/geodesic_n8.txt
Icarus/geodesic/ind_subsampling_n4_n5.txt
