Metadata-Version: 1.1
Name: Icarus
Version: 2.3.1
Summary: Icarus is a stellar binary light curve synthesis tool initially developed by Rene Breton
Home-page: https://github.com/bretonr/Icarus
Author: Dr Rene Breton
Author-email: superluminique@gmail.com
License: BSD
Download-URL: https://github.com/bretonr/Icarus/tarball/v2.3.0
Keywords: astrophysics,cosmology,photometry,binary,modeling,space,models,spectroscopy,astronomy,science,research,stars,physics
Platform: UNKNOWN
Classifier: Operating System :: OS Independent
Classifier: Development Status :: 5 - Production/Stable
Classifier: Intended Audience :: Science/Research
Classifier: Topic :: Scientific/Engineering :: Physics
Classifier: Topic :: Scientific/Engineering :: Astronomy
Classifier: License :: OSI Approved :: BSD License
Classifier: Programming Language :: Python :: 2
Classifier: Programming Language :: Python :: 2.7
Classifier: Programming Language :: Python :: 3
Classifier: Programming Language :: Python :: 3.3
Classifier: Programming Language :: Python :: 3.4
Classifier: Programming Language :: Python :: 3.5
